{
  "info": {
    "name": "Simplified API",
    "description": "API collection for Simplified task management app",
    "schema": "https://schema.getpostman.com/json/collection/v2.1.0/collection.json"
  },
  "variable": [
    {
      "key": "base_url",
      "value": "http://localhost:5000",
      "type": "string"
    },
    {
      "key": "auth_token",
      "value": "",
      "type": "string"
    }
  ],
  "item": [
    {
      "name": "Authentication",
      "item": [
        {
          "name": "Register User",
          "request": {
            "method": "POST",
            "header": [
              {
                "key": "Content-Type",
                "value": "application/json"
              }
            ],
            "body": {
              "mode": "raw",
              "raw": "{\n    \"username\": \"testuser\",\n    \"email\": \"test@example.com\",\n    \"password\": \"password123\"\n}"
            },
            "url": {
              "raw": "{{base_url}}/api/auth/register",
              "host": ["{{base_url}}"],
              "path": ["api", "auth", "register"]
            }
          }
        },
        {
          "name": "Login User",
          "request": {
            "method": "POST",
            "header": [
              {
                "key": "Content-Type",
                "value": "application/json"
              }
            ],
            "body": {
              "mode": "raw",
              "raw": "{\n    \"email\": \"test@example.com\",\n    \"password\": \"password123\"\n}"
            },
            "url": {
              "raw": "{{base_url}}/api/auth/login",
              "host": ["{{base_url}}"],
              "path": ["api", "auth", "login"]
            }
          },
          "event": [
            {
              "listen": "test",
              "script": {
                "exec": [
                  "if (pm.response.code === 200) {",
                  "    const response = pm.response.json();",
                  "    pm.collectionVariables.set('auth_token', response.token);",
                  "}"
                ]
              }
            }
          ]
        }
      ]
    },
    {
      "name": "Lists",
      "item": [
        {
          "name": "Get Lists",
          "request": {
            "method": "GET",
            "header": [
              {
                "key": "Authorization",
                "value": "Bearer {{auth_token}}"
              }
            ],
            "url": {
              "raw": "{{base_url}}/api/lists",
              "host": ["{{base_url}}"],
              "path": ["api", "lists"]
            }
          }
        },
        {
          "name": "Create List",
          "request": {
            "method": "POST",
            "header": [
              {
                "key": "Content-Type",
                "value": "application/json"
              },
              {
                "key": "Authorization",
                "value": "Bearer {{auth_token}}"
              }
            ],
            "body": {
              "mode": "raw",
              "raw": "{\n    \"title\": \"My Test List\",\n    \"category\": \"Work\"\n}"
            },
            "url": {
              "raw": "{{base_url}}/api/lists",
              "host": ["{{base_url}}"],
              "path": ["api", "lists"]
            }
          }
        }
      ]
    }
  ]
}